py.typed
occpy/_occpy.pyi
occpy/__init__.py
occpy/_occpy.cpython-310-darwin.so
bin/occ
include/occ/dma/dma.h
include/occ/dma/binomial.h
include/occ/dma/multipole_calculator.h
include/occ/dma/gauss_hermite.h
include/occ/dma/mult.h
include/occ/dma/linear_multipole_calculator.h
include/occ/dma/linear_multipole_shifter.h
include/occ/dma/add_qlm.h
include/occ/dma/multipole_shifter.h
include/occ/dma/solid_harmonics.h
occpy-0.8.6.dist-info/RECORD
occpy-0.8.6.dist-info/WHEEL
occpy-0.8.6.dist-info/entry_points.txt
occpy-0.8.6.dist-info/METADATA
occpy-0.8.6.dist-info/licenses/LICENSE.txt
share/occ/methods/dft_methods.json
share/occ/solvent/dielectric_constants.json
share/occ/solvent/dielectrics.json
share/occ/solvent/smd.json
share/occ/solvent/draco.json
share/occ/basis/pcseg-0.json
share/occ/basis/def2-tzvp-rifit.json
share/occ/basis/3-21g.json
share/occ/basis/def2-tzvpd.json
share/occ/basis/sap_grasp_small.json
share/occ/basis/def2-tzvp.json
share/occ/basis/cc-pvqz.json
share/occ/basis/mini.json
share/occ/basis/cc-pv5z.json
share/occ/basis/sap_grasp_large.json
share/occ/basis/def2-mtzvpp.json
share/occ/basis/def2-tzvppd.json
share/occ/basis/def2-tzvpp.json
share/occ/basis/pcseg-1.json
share/occ/basis/aug-pcseg-3.json
share/occ/basis/thakkar_original.json
share/occ/basis/def2-mtzvpp-rij.json
share/occ/basis/def2-svp.json
share/occ/basis/cc-pvtz.json
share/occ/basis/6-31g.json
share/occ/basis/cc-pvtz-f12.json
share/occ/basis/def2-sv(p).json
share/occ/basis/def2-universal-jkfit.json
share/occ/basis/cc-pv6z.json
share/occ/basis/aug-pcseg-2.json
share/occ/basis/aug-pcseg-1.json
share/occ/basis/sto-3g.json
share/occ/basis/def2-universal-jfit.json
share/occ/basis/cc-pv5z-jkfit.json
"share/occ/basis/6-311g(d,p).json"
share/occ/basis/def2-svpd.json
share/occ/basis/aug-pcseg-0.json
share/occ/basis/cc-pvqz-f12.json
share/occ/basis/cc-pvdz-f12.json
share/occ/basis/cc-pvdz.json
share/occ/basis/pcseg-2.json
share/occ/basis/def2-qzvp.json
share/occ/basis/cc-pvqz-jkfit.json
"share/occ/basis/6-31g(d,p).json"
share/occ/basis/def2-qzvpp.json
share/occ/basis/cc-pvtz-jkfit.json
