Metadata-Version: 2.1
Name: occpy
Version: 0.8.6
Summary: A library for quantum chemistry
Author-Email: Peter Spackman <peterspackman@fastmail.com>
Classifier: License :: OSI Approved :: GNU General Public License v3 or later (GPLv3+)
Project-URL: Homepage, https://github.com/peterspackman/occ
Requires-Python: >=3.10
Requires-Dist: numpy>1.24.4
